setup.py
html5forms/__init__.py
html5forms/fields.py
html5forms/models.py
html5forms/tests.py
html5forms/util.py
html5forms/views.py
html5forms/widgets.py
html5forms.egg-info/PKG-INFO
html5forms.egg-info/SOURCES.txt
html5forms.egg-info/dependency_links.txt
html5forms.egg-info/top_level.txt