Metadata-Version: 1.1
Name: html5forms
Version: 0.0.3
Summary: HTML5 forms for Django.
Home-page: https://github.com/adamcupial/django-html5-forms
Author: Adam Cupiał
Author-email: UNKNOWN
License: UNKNOWN
Platform: any
Classifier: Development Status :: 4 - Beta
Classifier: Intended Audience :: Developers
Classifier: License :: OSI Approved :: MIT License
Classifier: Operating System :: OS Independent
Classifier: Programming Language :: Python
Classifier: Topic :: Text Processing :: Markup :: HTML
Classifier: Topic :: Software Development :: Libraries :: Python Modules
